undoable_transaction/__init__.py
undoable_transaction/transaction.py
undoable_transaction-0.1.0.dist-info/DESCRIPTION.rst
undoable_transaction-0.1.0.dist-info/METADATA
undoable_transaction-0.1.0.dist-info/RECORD
undoable_transaction-0.1.0.dist-info/WHEEL
undoable_transaction-0.1.0.dist-info/metadata.json
undoable_transaction-0.1.0.dist-info/top_level.txt
undoable_transaction-0.1.0.dist-info/zip-safe
